ali_integral/__init__.py
ali_integral/config.py
ali_integral/eht_imaging.py
ali_integral/kerr_metric.py
ali_integral/pdf_generator.py
ali_integral/physics.py
ali_integral/plotting.py
ali_integral/utils.py
ali_integral/visualizer.py
ali_integral/visualizer_eht.py
ali_integral-1.2.0.dist-info/licenses/LICENSE
ali_integral-1.2.0.dist-info/METADATA
ali_integral-1.2.0.dist-info/WHEEL
ali_integral-1.2.0.dist-info/top_level.txt
ali_integral-1.2.0.dist-info/RECORD
