Metadata-Version: 2.4
Name: ali_integral
Version: 1.2.0
Summary: A Python library for calculating Information Flux at the Cauchy Horizon
Home-page: https://github.com/Troxter222/Ali_Integral_Project
Author: Ali (Troxter222)
Classifier: Programming Language :: Python :: 3
Classifier: License :: OSI Approved :: MIT License
Classifier: Operating System :: OS Independent
License-File: LICENSE
Requires-Dist: numpy
Requires-Dist: matplotlib
Requires-Dist: scipy
Requires-Dist: imageio
Dynamic: author
Dynamic: classifier
Dynamic: description
Dynamic: description-content-type
Dynamic: home-page
Dynamic: license-file
Dynamic: requires-dist
Dynamic: summary
